web3abi/BalancerV2.py
web3abi/Curve.py
web3abi/UniswapV2.py
web3abi/__init__.py
web3abi/json/Curve_3coin_pool.json
web3abi/json/Curve_tricrypto.json
web3abi/json/Curve_tricrypto_math.json
web3abi/json/Curve_tricrypto_view.json
web3abi/json/UniswapV2Factory.json
web3abi/json/UniswapV2Pair.json
web3abi/json/UniswapV2Router.json
web3abi/json/Vault.json
web3abi/json/WeightedPool.json
web3abi/json/WeightedPool2Tokens.json
web3_abi-0.0.2.dist-info/LICENSE
web3_abi-0.0.2.dist-info/METADATA
web3_abi-0.0.2.dist-info/WHEEL
web3_abi-0.0.2.dist-info/top_level.txt
web3_abi-0.0.2.dist-info/RECORD
