Metadata-Version: 2.1
Name: web3-abi
Version: 0.0.2
Summary: Useful web3 abi
Home-page: https://github.com/powei-lin/web3-abi
Author: Powei Lin
Author-email: poweilin1994@gmail.com
License: UNKNOWN
Project-URL: Bug Tracker, https://github.com/powei-lin/web3-abi/issues
Platform: UNKNOWN
Classifier: Programming Language :: Python :: 3
Classifier: License :: OSI Approved :: MIT License
Classifier: Operating System :: OS Independent
Requires-Python: >=3.6
License-File: LICENSE
